__paths__.py
notebooks/__init__.py
notebooks/blm/__init__.py
notebooks/blm/bolima.yml
notebooks/blm/pos_statistics/__init__.py
notebooks/blm/pos_statistics/pos_statistics.ipynb
notebooks/blm/pos_statistics/pos_statistics.py
notebooks/blm/pos_statistics/pos_statistics_gui.py
notebooks/blm/topic_modelling/__init__.py
notebooks/blm/topic_modelling/explore.ipynb
notebooks/blm/topic_modelling/explore.py
notebooks/blm/word_trends/__init__.py
notebooks/blm/word_trends/word_trends.ipynb
notebooks/blm/word_trends/word_trends.py
notebooks/blm/word_trends/word_trends_gui.py
notebooks/litteraturbanken/__init__.py
notebooks/litteraturbanken/topic_modelling/__init__.py
notebooks/litteraturbanken/topic_modelling/explore.ipynb
notebooks/litteraturbanken/topic_modelling/explore.py
notebooks/novels/__init__.py
notebooks/novels/topic_modelling/__init__.py
notebooks/novels/topic_modelling/explore.ipynb
notebooks/novels/topic_modelling/explore.py
notebooks/other/__init__.py
notebooks/other/most_discriminating_words/__init__.py
notebooks/other/most_discriminating_words/most_discriminating_terms.ipynb
notebooks/other/most_discriminating_words/most_discriminating_terms.py
notebooks/other/scratchpad.ipynb
notebooks/other/scratchpad.py
notebooks/political_in_newspapers/__init__.py
notebooks/political_in_newspapers/most_discriminating_words/4_mdw.ipynb
notebooks/political_in_newspapers/most_discriminating_words/4_mdw.py
notebooks/political_in_newspapers/most_discriminating_words/__init__.py
notebooks/political_in_newspapers/most_discriminating_words/mdw_gui.py
notebooks/political_in_newspapers/named_entity_recognition/__init__.py
notebooks/political_in_newspapers/named_entity_recognition/bert_kb_ner.py
notebooks/political_in_newspapers/named_entity_recognition/named_entity_recognition.ipynb
notebooks/political_in_newspapers/named_entity_recognition/named_entity_recognition.py
notebooks/political_in_newspapers/topic_modelling/0_convert_data_files.R
humlab_westac-0.5.40.dist-info/METADATA
humlab_westac-0.5.40.dist-info/WHEEL
humlab_westac-0.5.40.dist-info/entry_points.txt
humlab_westac-0.5.40.dist-info/RECORD
