Metadata-Version: 2.1
Name: humlab-westac
Version: 0.5.40
Summary: Welfare State Analytics
Home-page: https://westac.se
License: Apache-2.0
Author: Roger Mähler
Author-email: roger.mahler@hotmail.com
Requires-Python: ==3.11.*
Classifier: License :: OSI Approved :: Apache Software License
Classifier: Operating System :: OS Independent
Classifier: Programming Language :: Python
Classifier: Programming Language :: Python :: 3
Classifier: Programming Language :: Python :: 3.11
Classifier: Topic :: Software Development
Requires-Dist: PyGithub (>=1.55,<2.0)
Requires-Dist: bar-chart-race (>=0.1.0,<0.2.0)
Requires-Dist: bokeh
Requires-Dist: bqplot (>=0.12.32,<0.13.0)
Requires-Dist: click
Requires-Dist: humlab-penelope[full] (==0.7.68)
Requires-Dist: ipydatagrid (>=1.1.8,<2.0.0)
Requires-Dist: ipywidgets
Requires-Dist: jupyterlab (==3.*)
Requires-Dist: loguru (>=0.5.3,<0.6.0)
Requires-Dist: matplotlib
Requires-Dist: msgpack (>=1.0.2,<2.0.0)
Requires-Dist: nltk
Requires-Dist: pandas (<2.0.0)
Requires-Dist: pandas-bokeh
Requires-Dist: plotly (>=5.5.0,<6.0.0)
Requires-Dist: scikit-learn
Requires-Dist: scipy
Requires-Dist: tqdm
Requires-Dist: urllib3 (==1.26.15)
Project-URL: Repository, https://github.com/welfare-state-analytics/welfare_state_analytics
